enode_quant/__init__.py
enode_quant/client.py
enode_quant/config.py
enode_quant/errors.py
enode_quant/api/candles.py
enode_quant/api/options.py
enode_quant/api/stocks.py
enode_quant/cli/login.py
enode_quant/cli/logout.py
enode_quant/cli/main.py
enode_quant/cli/whoami.py
enode_quant/sql/option_queries.py
enode_quant/sql/stock_queries.py
enode_quant/sql/utils.py
enode_quant/utils/df_helpers.py
enode_quant/utils/validation.py
enode_quant-0.1.8.dist-info/METADATA
enode_quant-0.1.8.dist-info/WHEEL
enode_quant-0.1.8.dist-info/entry_points.txt
enode_quant-0.1.8.dist-info/top_level.txt
enode_quant-0.1.8.dist-info/RECORD
