Metadata-Version: 2.4
Name: enode-quant
Version: 0.1.8
Summary: Add your description here
Author: Oscar Thiele Serrano
Requires-Python: >=3.11
Requires-Dist: pandas>=2.3.3
Requires-Dist: requests>=2.32.5
Requires-Dist: typer>=0.20.0
